{
  "kind": "collectionType",
  "connection": "default",
  "collectionName": "brews",
  "info": {
    "name": "Brews"
  },
  "options": {
    "increments": true,
    "timestamps": true
  },
  "attributes": {
    "description": {
      "type": "richtext"
    },
    "name": {
      "type": "string"
    },
    "image": {
      "collection": "file",
      "via": "related",
      "plugin": "upload",
      "required": false
    },
    "price": {
      "type": "decimal"
    },
    "brand": {
      "model": "brand",
      "via": "brews"
    }
  }
}
